pixigpt/__init__.py
pixigpt/client.py
pixigpt/errors.py
pixigpt/types.py
pixigpt-0.1.5.dist-info/METADATA
pixigpt-0.1.5.dist-info/WHEEL
pixigpt-0.1.5.dist-info/top_level.txt
pixigpt-0.1.5.dist-info/RECORD
