Metadata-Version: 2.1
Name: pixigpt
Version: 0.1.5
Summary: Production-grade Python client for the PixiGPT API
Author-email: PixiGPT <contact@pixigpt.com>
License: MIT
Project-URL: Homepage, https://github.com/PixiGPT/pixigpt-py
Project-URL: Documentation, https://pixigpt.com/docs
Project-URL: Repository, https://github.com/PixiGPT/pixigpt-py
Keywords: pixigpt,llm,ai,api,client
Classifier: Development Status :: 4 - Beta
Classifier: Intended Audience :: Developers
Classifier: License :: OSI Approved :: MIT License
Classifier: Programming Language :: Python :: 3
Classifier: Programming Language :: Python :: 3.8
Classifier: Programming Language :: Python :: 3.9
Classifier: Programming Language :: Python :: 3.10
Classifier: Programming Language :: Python :: 3.11
Classifier: Programming Language :: Python :: 3.12
Requires-Python: >=3.8
Requires-Dist: requests>=2.31.0
Requires-Dist: urllib3>=2.0.0
Provides-Extra: dev
Requires-Dist: pytest>=7.0.0; extra == "dev"
Requires-Dist: python-dotenv>=1.0.0; extra == "dev"
Requires-Dist: twine>=5.0.0; extra == "dev"
Requires-Dist: build>=1.0.0; extra == "dev"
